{
  "book": {
    "id": 1,
    "name": "창세기",
    "contents": {
      "chapter_number": 26,
      "paragraph_summary": [
        {
          "paragraph": 1,
          "title": "이삭, 그랄에서 번성하다",
          "details": [
            "아브라함 시대에 이어 또 흉년이 들자 이삭은 블레셋 왕 아비멜렉에게로 감.",
            "하나님은 이삭에게 애굽으로 가지 말고 지시하는 땅에 거주하라 명하시고 아브라함에게 약속하신 복을 주겠다고 약속하심.",
            "이삭은 그랄에 거주하며, 아내 리브가를 누이라 속임. 아비멜렉이 이를 알고 이삭을 책망함."
          ]
        },
        {
          "paragraph": 2,
          "title": "우물 분쟁과 르호봇",
          "details": [
            "이삭은 그랄에서 농사지어 백 배의 수확을 얻고 거부가 됨. 블레셋 사람들은 그를 시기함.",
            "아비멜렉은 이삭에게 떠나라고 요구함. 이삭은 그랄 골짜기에 장막을 치고 아브라함이 팠던 우물들을 다시 팜.",
            "이삭의 종들이 샘 근원을 얻었으나 그랄 목자들이 다툼. 이삭은 우물 이름을 에섹, 싯나라 지음.",
            "다툼이 없는 우물을 파고 르호봇이라 이름하며 번성을 기원함."
          ]
        },
        {
          "paragraph": 3,
          "title": "브엘세바와 아비멜렉과의 계약",
          "details": [
            "이삭은 브엘세바로 올라감. 하나님은 그에게 나타나 아브라함을 위하여 복을 주어 자손을 번성하게 하겠다고 약속하심.",
            "이삭은 그 곳에 제단을 쌓고 여호와의 이름을 부름.",
            "아비멜렉이 아훗삿, 비골과 함께 이삭을 찾아와 평화 조약을 맺음.",
            "이삭은 잔치를 베풀고 그들을 평안히 보냄."
          ]
        },
        {
          "paragraph": 4,
          "title": "브엘세바와 에서의 결혼",
          "details": [
            "이삭의 종들이 우물을 발견하고 세바라 이름 지음. 그 성읍 이름이 브엘세바가 됨.",
            "에서가 헷 족속 여인들과 결혼하여 이삭과 리브가의 마음에 근심이 됨."
          ]
        }
      ]
    }
  }
}