{
  "book": {
    "id": 14,
    "name": "역대하",
    "contents": {
      "chapter_number": 11,
      "paragraph_summary": [
        {
          "paragraph": 1,
          "title": "르호보암의 군대 동원과 스마야의 예언",
          "details": [
            "르호보암이 이스라엘과 싸우려 18만 명의 용사를 모았으나, 하나님의 말씀으로 스마야가 전쟁을 막음",
            "하나님의 말씀에 순종하여 군대가 되돌아감"
          ]
        },
        {
          "paragraph": 2,
          "title": "르호보암의 성읍 방비",
          "details": [
            "르호보암이 유다 땅에 방비하는 성읍들을 건축하고 견고하게 함",
            "각 성읍에 지휘관을 두고 양식, 기름, 포도주를 저축하고 방패와 창을 둠"
          ]
        },
        {
          "paragraph": 3,
          "title": "제사장과 레위 사람들의 귀환",
          "details": [
            "여로보암이 제사장 직분을 빼앗자, 제사장들과 레위 사람들이 르호보암에게 돌아옴",
            "여로보암이 산당, 우상을 위해 제사장을 세움"
          ]
        },
        {
          "paragraph": 4,
          "title": "유다의 강성",
          "details": [
            "마음을 굳게 하여 하나님을 찾는 자들이 레위인들을 따라 예루살렘으로 돌아옴",
            "3년 동안 다윗과 솔로몬의 길로 행하여 르호보암이 강성해짐"
          ]
        },
        {
          "paragraph": 5,
          "title": "르호보암의 아내와 자녀",
          "details": [
            "르호보암이 여러 아내를 두어 많은 아들과 딸을 낳음",
            "압살롬의 딸 마아가를 가장 사랑하여, 그의 아들 아비야를 후계자로 세움",
            "르호보암이 아들들을 성읍에 흩어 살게 하고 양식을 후히 줌"
          ]
        }
      ]
    }
  }
}