{
  "book": {
    "id": 19,
    "name": "시편",
    "contents": {
      "chapter_number": 93,
      "paragraph_summary": [
        {
          "paragraph": 1,
          "title": "여호와의 통치와 능력",
          "details": [
            "여호와께서 권위를 입으시고 능력의 옷을 입으심",
            "세계가 견고히 서서 흔들리지 않음",
            "주의 보좌는 예로부터 견고히 섰으며 주는 영원부터 계심"
          ]
        },
        {
          "paragraph": 2,
          "title": "여호와의 능력의 위대함",
          "details": [
            "큰 물의 소리보다 높이 계신 여호와의 능력이 더 큼",
            "바다의 큰 파도보다 여호와의 능력이 더 큼"
          ]
        },
        {
          "paragraph": 3,
          "title": "여호와의 증거와 거룩함",
          "details": [
            "주의 증거들이 매우 확실함",
            "거룩함이 주의 집에 합당함",
            "여호와는 영원무궁하심"
          ]
        }
      ]
    }
  }
}