{
  "book": {
    "id": 23,
    "name": "이사야",
    "contents": {
      "chapter_number": 60,
      "paragraph_summary": [
        {
          "paragraph": 1,
          "title": "일어나 빛을 발하라",
          "details": [
            "여호와의 영광이 임하였으니 일어나 빛을 발하라.",
            "어둠이 땅을 덮으나 여호와께서 네 위에 임하시고 그의 영광이 네 위에 나타나리니 나라들이 네 빛으로 나아오리라."
          ]
        },
        {
          "paragraph": 2,
          "title": "열방의 귀환과 번영",
          "details": [
            "무리들이 네게로 모여들고 네 아들딸들이 돌아오리라.",
            "바다의 부와 이방 나라들의 재물이 네게로 돌아오며 낙타와 금과 유향을 가지고 여호와를 찬송하리라.",
            "게달의 양과 느바욧의 숫양이 네 제단에 기꺼이 받음이 되며 내가 내 영광의 집을 영화롭게 하리라."
          ]
        },
        {
          "paragraph": 3,
          "title": "하나님의 영화롭게 하심",
          "details": [
            "섬들과 다시스의 배들이 네 자손과 은금을 싣고 와서 여호와께 드리리니 이는 내가 너를 영화롭게 하였음이라.",
            "이방인들이 네 성벽을 쌓고 그들의 왕들이 너를 섬기리라.",
            "노하여 너를 쳤으나 이제는 나의 은혜로 불쌍히 여겼음이라."
          ]
        },
        {
          "paragraph": 4,
          "title": "영원한 아름다움과 기쁨",
          "details": [
            "네 성문이 항상 열려 이방 나라들의 재물을 가져오게 하리라.",
            "너를 섬기지 않는 백성과 나라는 파멸하리라.",
            "레바논의 영광이 네게 이르러 내 거룩한 곳을 아름답게 하리라.",
            "너를 괴롭히던 자들이 네 발 아래 엎드려 너를 여호와의 성읍이라 부르리라.",
            "전에는 버림받았으나 이제는 영원한 아름다움과 기쁨이 되게 하리라."
          ]
        },
        {
          "paragraph": 5,
          "title": "하나님의 구원과 영광",
          "details": [
            "이방 나라들의 젖을 빨며 뭇 왕의 젖을 빨고 나 여호와는 네 구원자요 구속자임을 알리라.",
            "금을 가지고 놋을 대신하며 은을 가지고 철을 대신하는 등 더 나은 것으로 채우리라.",
            "강포와 황폐와 파멸이 다시 없을 것이며 네 성벽을 구원, 네 성문을 찬송이라 부르리라.",
            "해가 네 빛이 되지 않고 여호와가 네 영원한 빛이 되며 네 슬픔의 날이 끝날 것이라."
          ]
        },
        {
          "paragraph": 6,
          "title": "의로운 백성과 하나님의 약속",
          "details": [
            "네 백성이 다 의롭게 되어 영원히 땅을 차지하리니 이는 내가 심은 가지요 내가 손으로 만든 것이라.",
            "작은 자가 천 명을 이루고 약한 자가 강국을 이룰 것이라. 때가 되면 나 여호와가 속히 이루리라."
          ]
        }
      ]
    }
  }
}