{
  "book": {
    "id": 28,
    "name": "호세아",
    "contents": {
      "chapter_number": 12,
      "paragraph_summary": [
        {
          "paragraph": 1,
          "title": "에브라임의 죄와 하나님의 심판",
          "details": [
            "에브라임은 거짓과 포학을 더하며 앗수르, 애굽과 계약을 맺음",
            "여호와께서 유다와 논쟁하시고 야곱의 행실대로 보응하실 것임",
            "야곱은 모태에서 형의 발뒤꿈치를 잡고 하나님과 겨루어 이김",
            "하나님은 벧엘에서 야곱을 만나 말씀하셨음",
            "여호와는 만군의 하나님이시며 기억하게 하는 이름이심"
          ]
        },
        {
          "paragraph": 2,
          "title": "돌아오라는 하나님의 촉구와 에브라임의 교만",
          "details": [
            "하나님께로 돌아와 인애와 정의를 지키며 하나님을 바랄 것을 촉구",
            "에브라임은 거짓 저울을 사용하며 속이기를 좋아함",
            "에브라임은 자신이 부자라 죄가 없다고 주장하나, 하나님은 애굽에서부터 그들의 하나님이셨음",
            "하나님께서 다시 장막에 거주하게 하실 것임"
          ]
        },
        {
          "paragraph": 3,
          "title": "길르앗과 길갈의 죄악, 야곱의 과거와 에브라임의 격노",
          "details": [
            "길르앗은 거짓되며, 길갈에서는 수송아지로 제사를 드림",
            "야곱은 아람의 들로 도망하여 아내를 얻기 위해 종살이함",
            "하나님께서는 선지자를 통해 이스라엘을 애굽에서 인도하심",
            "에브라임이 하나님을 극심하게 격노하게 했으므로, 하나님께서 그의 피와 수치를 그에게 돌리실 것임"
          ]
        }
      ]
    }
  }
}