{
  "book": {
    "id": 7,
    "name": "사사기",
    "contents": {
      "chapter_number": 8,
      "paragraph_summary": [
        {
          "paragraph": 1,
          "title": "에브라임 사람들과 기드온의 다툼과 화해",
          "details": [
            "에브라임 사람들이 기드온에게 미디안과의 전투에 자신들을 부르지 않은 것을 항의하며 다툼.",
            "기드온은 에브라임의 끝물 포도가 아비에셀의 맏물 포도보다 낫다며 그들의 공로를 치켜세우고, 하나님이 미디안 방백들을 넘겨주신 것을 상기시켜 노여움을 풀게 함."
          ]
        },
        {
          "paragraph": 2,
          "title": "숙곳과 브누엘 사람들의 냉대와 보복",
          "details": [
            "기드온과 그의 군사들이 숙곳에 이르러 백성들에게 떡을 요청했으나 거절당함.",
            "브누엘에서도 같은 요청을 했으나 숙곳과 마찬가지로 거절당함.",
            "기드온은 승리 후 숙곳 사람들을 들가시와 찔레로 징벌하고, 브누엘 망대를 헐고 사람들을 죽임."
          ]
        },
        {
          "paragraph": 3,
          "title": "미디안 왕 세바와 살문나 처형",
          "details": [
            "기드온이 미디안의 두 왕 세바와 살문나를 사로잡아 처형함.",
            "다볼에서 죽인 자들에 대한 복수로, 맏아들 여델에게 처형을 명했으나 실패, 결국 기드온이 직접 처형함."
          ]
        },
        {
          "paragraph": 4,
          "title": "기드온의 거절과 에봇 제작",
          "details": [
            "이스라엘 백성들이 기드온에게 왕이 되어달라고 요청했으나, 기드온은 하나님만이 그들을 다스릴 것이라며 거절함.",
            "기드온은 전리품으로 얻은 금으로 에봇을 만들어 오브라에 두었으나, 이스라엘 백성들이 그것을 숭배하여 올무가 됨."
          ]
        },
        {
          "paragraph": 5,
          "title": "기드온의 죽음과 이스라엘의 배신",
          "details": [
            "기드온 통치 기간 동안 이스라엘은 평온했으나, 기드온이 죽은 후 바알을 숭배하고 바알브릿을 신으로 삼음.",
            "하나님과 기드온의 은혜를 잊고 배신함."
          ]
        }
      ]
    }
  }
}