{
  "questions": {
    "q1": {
      "id": 1,
      "_theory": "ACT(Hayes) 현재-순간 알아차림: '오늘 가장 많이'(분석·빈도)→'지금 이 순간'(체험·현재)으로 전환. Plutchik(1980) 기본 감정 분류 + Seligman 쾌락-의미 구분으로 joy/pleasure 명확히 분리. 욕망 stigma 제거(Deci&Ryan SDT). 옵션 표현 공감적 문장형으로 강화.",
      "question": "지금 이 순간, 마음속에 가장 크게 자리한 감정이 무엇인가요?",
      "type": "single",
      "options": [
        {
          "id": "joy",
          "_theory": "Seligman 의미 기반 기쁨(Eudaimonic Joy): 성취·감사에서 오는 깊고 충만한 기쁨 — pleasure의 가벼운 쾌락과 구분",
          "text": "이루어진 일이나 감사한 것이 있어 마음이 따뜻하고 벅차요 😊",
          "tags": ["joy", "gratitude"],
          "category": "positive"
        },
        {
          "id": "anger",
          "_theory": "Lazarus(1991) 인지 평가 이론: '억울함+뜨거움' 표현이 분노의 신체적·인지적 체험을 동시에 포착해 공감적 식별 가능",
          "text": "억울하거나 화가 나서 마음이 뜨겁고 불편해요 😤",
          "tags": ["patience", "forgiveness"],
          "category": "negative"
        },
        {
          "id": "sorrow",
          "_theory": "슬픔과 우울의 공통 체험: '마음이 무겁다'는 신체 감각이 슬픔(grief)과 우울(depression) 모두를 포함해 넓은 스펙트럼 포착",
          "text": "마음이 무겁고 슬프거나 우울한 기분이 들어요 😢",
          "tags": ["comfort", "hope"],
          "category": "negative"
        },
        {
          "id": "pleasure",
          "_theory": "Seligman 쾌락 기반 기쁨(Hedonic Pleasure): 특별한 이유 없이 가볍고 설레는 감각 — joy의 의미 기반 충만함과 명확히 구분",
          "text": "마음이 가볍고 즐거워서 설레거나 유쾌해요 🥰",
          "tags": ["joy", "peace"],
          "category": "positive"
        },
        {
          "id": "love",
          "_theory": "Sternberg 사랑의 삼각형 이론: 낭만적 사랑만이 아닌 친밀감·헌신·보살핌 모두 포함하는 넓은 사랑 감정",
          "text": "소중한 사람이나 무언가가 마음에 가득하고 따뜻해요 💕",
          "tags": ["love", "gratitude"],
          "category": "positive"
        },
        {
          "id": "hate",
          "_theory": "Averill(1982) 분노·혐오 연속성: '미움+짜증'을 함께 제시해 강한 혐오와 일상적 짜증·불쾌감 모두 포착. '미워하는'→'불편함'으로 낙인 완화",
          "text": "누군가나 상황이 밉거나 짜증스러워 마음이 불편해요 😠",
          "tags": ["forgiveness", "peace"],
          "category": "negative"
        },
        {
          "id": "desire",
          "_theory": "Deci&Ryan(1985) 자기결정이론: '욕망(欲望)'의 부정적 낙인 제거 — 원함·바람은 자연스러운 인간 동기. '간절히 원하는 마음'으로 중립화",
          "text": "무언가를 간절히 원하고 바라는 마음이 있어요 🌟",
          "tags": ["trust", "wisdom"],
          "category": "neutral"
        }
      ]
    },
    "q2": {
      "joy": {
        "id": 2,
        "question": "기쁨과 감사의 이유는 무엇인가요?",
        "type": "single",
        "options": [
          { "id": "achievement", "text": "목표를 이루거나 성취했어요", "tags": ["gratitude", "joy", "faith"] },
          { "id": "relationship", "text": "소중한 사람과 좋은 시간을 보냈어요", "tags": ["love", "gratitude", "presence"] },
          { "id": "blessing", "text": "예상치 못한 축복을 받았어요", "tags": ["gratitude", "joy", "faith"] },
          { "id": "growth", "text": "내면의 성장을 느꼈어요", "tags": ["wisdom", "hope", "faith"] },
          { "id": "peace_found", "text": "마음의 평안을 찾았어요", "tags": ["peace", "rest", "gratitude"] }
        ]
      },
      "anger": {
        "id": 2,
        "question": "화나고 억울한 감정의 원인은 무엇인가요?",
        "type": "single",
        "options": [
          { "id": "unfair", "text": "부당한 대우를 받았어요", "tags": ["patience", "peace", "trust"] },
          { "id": "betrayal", "text": "믿었던 사람에게 배신당했어요", "tags": ["forgiveness", "healing", "trust"] },
          { "id": "misunderstood", "text": "오해를 받았어요", "tags": ["patience", "peace", "comfort"] },
          { "id": "ignored", "text": "무시당하거나 존중받지 못했어요", "tags": ["love", "courage", "strength"] },
          { "id": "helpless_anger", "text": "상황을 바꿀 수 없는 무력감", "tags": ["strength", "trust", "hope"] }
        ]
      },
      "sorrow": {
        "id": 2,
        "question": "슬픔의 원인은 무엇인가요?",
        "type": "single",
        "options": [
          { "id": "loss", "text": "소중한 사람/것을 잃었어요", "tags": ["comfort", "hope", "presence", "healing"] },
          { "id": "separation", "text": "이별이나 관계의 끝을 겪었어요", "tags": ["comfort", "healing", "hope"] },
          { "id": "failure", "text": "실패나 좌절을 경험했어요", "tags": ["hope", "courage", "strength"] },
          { "id": "regret", "text": "후회되는 일이 있어요", "tags": ["forgiveness", "healing", "peace"] },
          { "id": "loneliness", "text": "외로움과 고독함을 느껴요", "tags": ["presence", "love", "comfort"] }
        ]
      },
      "pleasure": {
        "id": 2,
        "question": "행복하고 즐거운 이유는 무엇인가요?",
        "type": "single",
        "options": [
          { "id": "good_news", "text": "좋은 소식을 들었어요", "tags": ["joy", "gratitude", "hope"] },
          { "id": "rest_pleasure", "text": "충분한 휴식을 취했어요", "tags": ["rest", "peace", "gratitude"] },
          { "id": "hobby", "text": "좋아하는 일을 했어요", "tags": ["joy", "peace", "gratitude"] },
          { "id": "connection", "text": "사람들과 즐거운 시간을 보냈어요", "tags": ["love", "joy", "presence"] },
          { "id": "natural_joy", "text": "특별한 이유 없이 그냥 좋아요", "tags": ["joy", "gratitude", "peace"] }
        ]
      },
      "love": {
        "id": 2,
        "question": "사랑의 마음은 어디서 왔나요?",
        "type": "single",
        "options": [
          { "id": "family_love", "text": "가족에 대한 사랑이에요", "tags": ["love", "gratitude", "presence"] },
          { "id": "friend_love", "text": "친구에 대한 우정이에요", "tags": ["love", "joy", "gratitude"] },
          { "id": "romantic_love", "text": "연인/배우자에 대한 사랑이에요", "tags": ["love", "joy", "hope"] },
          { "id": "compassion", "text": "어려운 이웃을 향한 마음이에요", "tags": ["love", "wisdom", "courage"] },
          { "id": "god_love", "text": "하나님의 사랑을 느껴요", "tags": ["love", "faith", "gratitude"] }
        ]
      },
      "hate": {
        "id": 2,
        "question": "미움의 감정은 어디서 왔나요?",
        "type": "single",
        "options": [
          { "id": "hurt_by", "text": "그 사람에게 상처받았어요", "tags": ["healing", "forgiveness", "comfort"] },
          { "id": "envy", "text": "시기심이나 질투를 느껴요", "tags": ["peace", "trust", "wisdom"] },
          { "id": "conflict", "text": "해결되지 않는 갈등이 있어요", "tags": ["forgiveness", "patience", "peace"] },
          { "id": "injustice", "text": "불의한 행동을 보았어요", "tags": ["courage", "wisdom", "patience"] },
          { "id": "self_hate", "text": "나 자신이 미워요", "tags": ["love", "healing", "comfort"] }
        ]
      },
      "desire": {
        "id": 2,
        "question": "어떤 것을 원하고 있나요?",
        "type": "single",
        "options": [
          { "id": "success", "text": "성공과 성취를 원해요", "tags": ["wisdom", "guidance", "strength"] },
          { "id": "recognition", "text": "인정받고 싶어요", "tags": ["love", "courage", "trust"] },
          { "id": "material", "text": "물질적인 것이 필요해요", "tags": ["trust", "wisdom", "peace"] },
          { "id": "relationship_desire", "text": "좋은 관계를 원해요", "tags": ["love", "hope", "patience"] },
          { "id": "change", "text": "현재 상황의 변화를 원해요", "tags": ["hope", "courage", "guidance"] }
        ]
      }
    },
    "q3": {
      "positive": {
        "id": 3,
        "_theory": "Fredrickson(2001) Broaden-and-Build / Savoring(Bryant&Veroff 2007) / PERMA(Seligman 2011) / 사회적 공유(Gable 2004) / Lyubomirsky(2008) 의도적 행복 활동 적용. '감정을 어떻게 할 것인가' → '이 기쁨을 어떻게 더 깊이 가꿀 것인가'로 질문 심화, 4→6개 선택지로 확장.",
        "question": "이 기쁜 마음을 어떻게 더 깊이 가꾸고 싶으세요?",
        "type": "single",
        "options": [
          {
            "id": "savor",
            "text": "이 순간을 천천히 음미하며 마음에 새기고 싶어요",
            "_theory": "Savoring(Bryant&Veroff 2007): 긍정 경험을 의식적으로 음미·연장하는 기술 — 헤도닉 적응을 늦추고 행복감 지속",
            "tags": ["gratitude", "peace", "rest"]
          },
          {
            "id": "share_joy",
            "text": "소중한 사람에게 이 기쁨을 표현하고 나누고 싶어요",
            "_theory": "Gable et al.(2004) 능동적 건설적 반응(ACR): 긍정 정서의 사회적 공유가 관계 만족도와 개인 행복감을 동시에 증폭",
            "tags": ["love", "joy", "presence"]
          },
          {
            "id": "deepen_gratitude",
            "text": "이 감사함이 더 깊어지도록 기도하고 묵상하고 싶어요",
            "_theory": "Emmons&McCullough(2003) 감사 개입: 감사 심화 연습이 웰빙·삶의 만족도·신앙 성장 모두에 유의미한 효과",
            "tags": ["gratitude", "faith", "love"]
          },
          {
            "id": "act_good",
            "text": "이 에너지로 누군가에게 선한 일을 하고 싶어요",
            "_theory": "Fredrickson(2001) Broaden-and-Build: 긍정 정서가 사고-행동 레퍼토리를 확장 → 친사회적 행동 동기와 심리적 자원을 함께 키움",
            "tags": ["love", "courage", "hope"]
          },
          {
            "id": "find_meaning",
            "text": "이 기쁨이 어디서 왔는지 그 의미를 깊이 찾고 싶어요",
            "_theory": "Seligman PERMA의 Meaning(의미): 긍정 경험을 삶의 의미·목적과 연결할 때 일시적 쾌락이 지속적 번영(Flourishing)으로 전환",
            "tags": ["wisdom", "faith", "gratitude"]
          },
          {
            "id": "plant_seed",
            "text": "이 행복이 내일로도 이어지도록 씨앗을 심고 싶어요",
            "_theory": "Lyubomirsky(2008) 의도적 행복 활동(Intentional Activity): 환경·유전이 아닌 의도적 행동이 지속적 행복 수준을 결정하는 핵심 변인",
            "tags": ["hope", "faith", "joy"]
          }
        ]
      },
      "negative": {
        "id": 3,
        "_theory": "CBT(Beck 1979) 자동적사고·인지왜곡 / 정서조절(Gross) / 애착이론(Bowlby) 기반. 표면 상황이 아닌 마음속 생각 패턴을 탐색하도록 질문 전환.",
        "question": "지금 마음속에서 가장 크게 들리는 목소리는 무엇인가요?",
        "type": "single",
        "options": [
          {
            "id": "pain_unseen",
            "text": "내 진짜 마음을 아무도 이해 못 할 것 같아요",
            "_theory": "애착이론(Bowlby): 연결 욕구 좌절 — 정서적 고립감",
            "tags": ["presence", "love", "comfort"]
          },
          {
            "id": "pain_helpless",
            "text": "내가 아무리 해도 달라지지 않을 것 같아요",
            "_theory": "CBT/Seligman: 학습된 무력감(Learned Helplessness) — 통제 불가 신념",
            "tags": ["hope", "strength", "faith"]
          },
          {
            "id": "pain_rumination",
            "text": "같은 생각이 계속 머릿속을 맴돌아요",
            "_theory": "CBT(Nolen-Hoeksema): 반추(Rumination) — 부정 사고 고리가 감정을 악화",
            "tags": ["peace", "rest", "healing"]
          },
          {
            "id": "pain_self_blame",
            "text": "이렇게 된 게 다 내 탓인 것 같아 자책돼요",
            "_theory": "CBT(Beck): 자기 귀인 오류(Self-blame) / 과잉 자기비난 인지왜곡",
            "tags": ["forgiveness", "love", "healing"]
          },
          {
            "id": "pain_fear",
            "text": "앞으로 더 나빠질 것 같아서 두려워요",
            "_theory": "CBT: 파국화(Catastrophizing) — 최악의 결과를 기정사실화",
            "tags": ["trust", "hope", "guidance"]
          },
          {
            "id": "pain_suppressed",
            "text": "화가 나지만 어디에도 표현할 수가 없어요",
            "_theory": "정서조절(Gross 2015): 억압(Suppression) — 표현되지 못한 감정의 누적·신체화",
            "tags": ["peace", "patience", "healing"]
          }
        ]
      },
      "neutral": {
        "id": 3,
        "_theory": "CBT(Ellis REBT) 좌절 내성·사회 비교(Festinger 1954) / ACT(Hayes) 인지 융합·가치 명료화 / Bandura(1977) 자기효능감 / Frankl(1959) 의미 혼란 / Neff 자기연민 적용. 단어형 선택지 4개 → 감정 문장형 6개로 욕구에 얽힌 인지 패턴을 정밀 탐색.",
        "question": "이 욕구나 바람을 떠올릴 때, 마음에서 가장 크게 느껴지는 것은 무엇인가요?",
        "type": "single",
        "options": [
          {
            "id": "desire_impatient",
            "text": "빨리 이루어지길 원하는데 자꾸 늦어져 답답하고 초조해요",
            "_theory": "Ellis REBT 좌절 내성 부족(Low Frustration Tolerance): '반드시 지금 이루어져야 한다'는 당위적 신념이 분노·좌절 유발",
            "tags": ["patience", "trust", "peace"]
          },
          {
            "id": "desire_comparison",
            "text": "남들은 이미 다 가지고 있는데 나만 없다는 박탈감이 들어요",
            "_theory": "Festinger(1954) 사회 비교 이론: 상향 비교(Upward Comparison)가 자존감 저하·상대적 박탈감을 유발 — 내적 기준 회복 필요",
            "tags": ["peace", "gratitude", "wisdom"]
          },
          {
            "id": "desire_doubt",
            "text": "과연 내가 이걸 이룰 수 있을지 스스로를 믿기가 어려워요",
            "_theory": "Bandura(1977) 자기효능감(Self-Efficacy) 부족: 역량에 대한 낮은 신념이 시도 자체를 억제 — 작은 성공 경험(Mastery Experience)으로 회복",
            "tags": ["courage", "faith", "hope"]
          },
          {
            "id": "desire_fusion",
            "text": "이 생각이 너무 커져서 다른 소중한 것들을 놓치고 있는 것 같아요",
            "_theory": "ACT(Hayes) 인지 융합(Cognitive Fusion): 욕구 생각과 자아가 합쳐져 다른 가치·관계를 보지 못함 — 탈융합(Defusion) 필요",
            "tags": ["peace", "wisdom", "rest"]
          },
          {
            "id": "desire_meaning",
            "text": "이걸 정말 원하는 건지, 왜 원하는 건지 스스로도 혼란스러워요",
            "_theory": "Frankl(1959) 의미 혼란 + ACT 가치 명료화(Values Clarification): 욕구가 외적 압력(인정·비교)인지 진짜 가치인지 분별 필요",
            "tags": ["wisdom", "guidance", "faith"]
          },
          {
            "id": "desire_guilt",
            "text": "이런 걸 바라는 내 자신이 너무 탐욕스럽게 느껴져 죄책감이 들어요",
            "_theory": "CBT 자기비판 + Neff(2011) 자기연민: 욕구 자체에 수치심을 갖는 패턴 — 인간적 욕구를 자연스럽게 수용하는 자기연민 필요",
            "tags": ["forgiveness", "love", "peace"]
          }
        ]
      }
    },
    "q4": {
      "positive": {
        "id": 4,
        "_theory": "긍정심리학 개입(PPIs) 직접 적용: Three Good Things(Seligman 2005) / Acts of Kindness(Lyubomirsky 2005) / Positive Bedtime Review(Savoring) / Spiritual Gratitude / Snyder 희망이론. '오늘을 어떻게 닫을 것인가'로 질문을 행동 지향적으로 구체화, 4→5개 선택지로 확장.",
        "question": "오늘 하나님이 허락하신 이 선함으로, 하루를 어떻게 마무리할까요?",
        "type": "single",
        "options": [
          {
            "id": "three_blessings",
            "text": "오늘 감사한 일 세 가지를 마음에 새기며 하루를 돌아보고 싶어요 📓",
            "_theory": "Seligman(2005) Three Good Things: 잠자리 전 세 가지 감사 회상이 우울감 감소·행복감 증가에 6개월 효과 지속 확인",
            "tags": ["gratitude", "peace", "faith"]
          },
          {
            "id": "kind_word",
            "text": "이 기쁨으로 소중한 사람에게 따뜻한 말 한마디를 건네고 싶어요 💌",
            "_theory": "Lyubomirsky(2005) Acts of Kindness: 타인을 위한 의도적 친절 행동이 행복의 지속성을 높이는 가장 효과적인 개입 중 하나",
            "tags": ["love", "joy", "presence"]
          },
          {
            "id": "restful_close",
            "text": "오늘의 좋은 순간들을 떠올리며 평안히 쉬고 싶어요 🌙",
            "_theory": "Positive Bedtime Review(Savoring): 수면 전 긍정 경험 회상이 수면의 질과 다음날 기분 상태를 유의미하게 개선",
            "tags": ["rest", "peace", "gratitude"]
          },
          {
            "id": "thanksgiving_prayer",
            "text": "하나님께 드리는 감사 기도로 오늘 하루를 마무리하고 싶어요 🙏",
            "_theory": "Spiritual Gratitude: 수직적 감사(하나님께)가 수평적 감사보다 삶의 의미감·영적 평안을 더 깊게 강화 — 성경적 감사의 완성",
            "tags": ["faith", "gratitude", "love"]
          },
          {
            "id": "hopeful_rest",
            "text": "내일도 이런 하루이길 소망하며 기대감으로 잠들고 싶어요 ✨",
            "_theory": "Snyder(1994) 희망이론: 긍정적 미래 기대(Hopeful Thinking)가 현재 웰빙과 도전 동기를 동시에 강화 — 오늘의 기쁨이 내일의 에너지",
            "tags": ["hope", "joy", "faith"]
          }
        ]
      },
      "negative": {
        "id": 4,
        "_theory": "ACT(Hayes 2004) 가치 기반 행동·자기연민(Neff) / 긍정심리학 회복탄력성(Seligman PERMA) / 애착이론 안전기지 / 정서조절 다운레귤레이션 적용. '무엇이 없는지'가 아닌 '어떤 내면 자원이 필요한지'로 질문 전환.",
        "question": "지금 이 아픔을 안고, 내면에서 가장 필요한 힘은 무엇인가요?",
        "type": "single",
        "options": [
          {
            "id": "need_acceptance",
            "text": "흔들려도 괜찮다는 자기 수용과 연민 🌿",
            "_theory": "ACT(Hayes) + Neff 자기연민(Self-Compassion): 완벽해야 한다는 압박에서 벗어나 있는 그대로 받아들이기",
            "tags": ["love", "healing", "comfort"]
          },
          {
            "id": "need_peace",
            "text": "복잡한 마음이 고요해질 수 있는 안정과 쉼 🕊️",
            "_theory": "정서조절(Gross): 과활성화된 감정 시스템을 다운레귤레이션하는 안정화",
            "tags": ["peace", "rest", "trust"]
          },
          {
            "id": "need_direction",
            "text": "다음 한 걸음을 볼 수 있는 빛과 방향 🧭",
            "_theory": "CBT 행동활성화(BA) + Snyder 희망이론: 목표-경로-의지력 3요소 중 경로감각 회복",
            "tags": ["guidance", "hope", "wisdom"]
          },
          {
            "id": "need_courage",
            "text": "다시 일어설 수 있다는 믿음과 용기 💪",
            "_theory": "긍정심리학(Seligman PERMA): 회복탄력성(Resilience) — 역경을 통해 강점이 단련됨",
            "tags": ["courage", "strength", "faith"]
          },
          {
            "id": "need_presence",
            "text": "이 마음을 알아주고 곁에 있어줄 누군가 🤗",
            "_theory": "애착이론(Bowlby): 안전 기지(Secure Base) 탐색 — 연결과 사회적 지지의 욕구",
            "tags": ["presence", "love", "comfort"]
          },
          {
            "id": "need_healing",
            "text": "상처가 천천히 아물어갈 수 있는 치유의 시간 💚",
            "_theory": "정서조절: 치유는 즉각적이지 않으며 시간과 과정이 필요함을 수용 — ACT의 수용(Acceptance)",
            "tags": ["healing", "comfort", "patience"]
          }
        ]
      },
      "neutral": {
        "id": 4,
        "_theory": "ACT(Hayes 2004) 가치 기반 행동·탈융합·수용 / 마음챙김(Kabat-Zinn) 현재 순간 / 자기결정이론(Deci&Ryan 1985) 자율성·내적 동기 / Frankl 의미치료 / Bandura 자기효능감. 단어형 4개 → 행동 지향 문장형 5개로 욕구와 함께 살아가는 내면 자원 탐색.",
        "question": "이 바람을 안고 살아가기 위해, 지금 내면에서 가장 필요한 것은 무엇인가요?",
        "type": "single",
        "options": [
          {
            "id": "want_discern",
            "text": "이 욕구가 진짜 내 삶의 가치에서 온 것인지 분별하고 싶어요 🔍",
            "_theory": "ACT 가치 명료화(Values Clarification) + Frankl(1959): 욕구의 원천을 파악해 외적 압력(비교·인정)과 진정한 가치 기반 욕구를 구분",
            "tags": ["wisdom", "guidance", "faith"]
          },
          {
            "id": "want_wait",
            "text": "이루어지는 데 걸리는 시간을 평안하게 기다릴 마음의 여유가 필요해요 ⏳",
            "_theory": "CBT 좌절 내성(Frustration Tolerance) 강화 + 정서조절 인내: 즉각적 충족을 기다리는 능력이 웰빙과 목표 달성 모두에 필수",
            "tags": ["patience", "trust", "peace"]
          },
          {
            "id": "want_content",
            "text": "지금 이 순간, 이미 충분함을 느끼는 감사와 평화가 필요해요 🍃",
            "_theory": "마음챙김(Kabat-Zinn) 현재 순간 수용 + 자기결정이론(Deci&Ryan) 내적 충족: 외적 목표보다 현재의 내적 풍요에서 행복이 온다",
            "tags": ["peace", "gratitude", "rest"]
          },
          {
            "id": "want_courage",
            "text": "원하는 것을 향해 두려움을 넘어 한 걸음 내딛는 용기가 필요해요 🌟",
            "_theory": "Bandura(1977) 자기효능감 강화 + ACT 가치 기반 행동(Committed Action): 결과 보장 없이도 가치에 따라 행동하는 용기",
            "tags": ["courage", "faith", "strength"]
          },
          {
            "id": "want_free",
            "text": "이 욕구에 끌려다니지 않고 내 삶의 주인이 되는 자유가 필요해요 🕊️",
            "_theory": "ACT 탈융합(Defusion) + 자기결정이론 자율성(Autonomy): 욕구를 소유하되 욕구에 지배당하지 않는 심리적 자유",
            "tags": ["peace", "wisdom", "trust"]
          }
        ]
      }
    }
  },
  "verses": [
    {
      "id": 1,
      "reference": "마태복음 11:28",
      "text": "수고하고 무거운 짐 진 자들아 다 내게로 오라 내가 너희를 쉬게 하리라",
      "tags": ["rest", "comfort", "strength"]
    },
    {
      "id": 2,
      "reference": "빌립보서 4:6-7",
      "text": "아무 것도 염려하지 말고 다만 모든 일에 기도와 간구로, 너희 구할 것을 감사함으로 하나님께 아뢰라 그리하면 모든 지각에 뛰어난 하나님의 평강이 그리스도 예수 안에서 너희 마음과 생각을 지키시리라",
      "tags": ["peace", "trust", "gratitude"]
    },
    {
      "id": 3,
      "reference": "시편 23:4",
      "text": "내가 사망의 음침한 골짜기로 다닐지라도 해를 두려워하지 않을 것은 주께서 나와 함께 하심이라 주의 지팡이와 막대기가 나를 안위하시나이다",
      "tags": ["comfort", "presence", "courage"]
    },
    {
      "id": 4,
      "reference": "이사야 41:10",
      "text": "두려워하지 말라 내가 너와 함께 함이라 놀라지 말라 나는 네 하나님이 됨이라 내가 너를 굳세게 하리라 참으로 너를 도와 주리라 참으로 나의 의로운 오른손으로 너를 붙들리라",
      "tags": ["strength", "courage", "presence"]
    },
    {
      "id": 5,
      "reference": "로마서 8:28",
      "text": "우리가 알거니와 하나님을 사랑하는 자 곧 그의 뜻대로 부르심을 입은 자들에게는 모든 것이 합력하여 선을 이루느니라",
      "tags": ["hope", "trust", "guidance"]
    },
    {
      "id": 6,
      "reference": "시편 46:1",
      "text": "하나님은 우리의 피난처시요 힘이시니 환난 중에 만날 큰 도움이시라",
      "tags": ["strength", "comfort", "presence"]
    },
    {
      "id": 7,
      "reference": "예레미야 29:11",
      "text": "여호와의 말씀이니라 너희를 향한 나의 생각을 내가 아나니 평안이요 재앙이 아니니라 너희에게 미래와 희망을 주는 것이니라",
      "tags": ["hope", "guidance", "trust"]
    },
    {
      "id": 8,
      "reference": "시편 34:18",
      "text": "여호와는 마음이 상한 자에게 가까이 하시고 충심으로 통회하는 자를 구원하시는도다",
      "tags": ["comfort", "presence", "healing"]
    },
    {
      "id": 9,
      "reference": "요한복음 14:27",
      "text": "평안을 너희에게 끼치노니 곧 나의 평안을 너희에게 주노라 내가 너희에게 주는 것은 세상이 주는 것과 같지 아니하니라 너희는 마음에 근심하지도 말고 두려워하지도 말라",
      "tags": ["peace", "comfort", "courage"]
    },
    {
      "id": 10,
      "reference": "고린도후서 1:3-4",
      "text": "찬송하리로다 그는 우리 주 예수 그리스도의 하나님이시요 자비의 아버지시요 모든 위로의 하나님이시며 우리의 모든 환난 중에서 우리를 위로하사 우리로 하여금 하나님께 받는 위로로써 모든 환난 중에 있는 자들을 능히 위로하게 하시는 이시로다",
      "tags": ["comfort", "love", "presence"]
    },
    {
      "id": 11,
      "reference": "시편 91:1-2",
      "text": "지존자의 은밀한 곳에 거주하는 자는 전능자의 그늘 아래에 살리로다 나는 여호와를 향하여 말하기를 그는 나의 피난처요 나의 요새요 내가 의뢰하는 하나님이라 하리로다",
      "tags": ["peace", "rest", "trust", "presence"]
    },
    {
      "id": 12,
      "reference": "잠언 3:5-6",
      "text": "너는 마음을 다하여 여호와를 신뢰하고 네 명철을 의지하지 말라 너는 범사에 그를 인정하라 그리하면 네 길을 지도하시리라",
      "tags": ["wisdom", "guidance", "trust"]
    },
    {
      "id": 13,
      "reference": "이사야 40:31",
      "text": "오직 여호와를 앙망하는 자는 새 힘을 얻으리니 독수리가 날개치며 올라감 같을 것이요 달음박질하여도 곤비하지 아니하겠고 걸어가도 피곤하지 아니하리로다",
      "tags": ["strength", "hope", "rest"]
    },
    {
      "id": 14,
      "reference": "시편 55:22",
      "text": "네 짐을 여호와께 맡기라 그가 너를 붙드시고 의인의 요동함을 영원히 허락하지 아니하시리로다",
      "tags": ["rest", "trust", "comfort"]
    },
    {
      "id": 15,
      "reference": "요한일서 4:18",
      "text": "사랑 안에 두려움이 없고 온전한 사랑이 두려움을 내쫓나니 두려움에는 형벌이 있음이라 두려워하는 자는 사랑 안에서 온전히 이루지 못하였느니라",
      "tags": ["love", "peace", "courage"]
    },
    {
      "id": 16,
      "reference": "시편 27:1",
      "text": "여호와는 나의 빛이요 나의 구원이시니 내가 누구를 두려워하리요 여호와는 내 생명의 능력이시니 내가 누구를 무서워하리요",
      "tags": ["courage", "strength", "faith"]
    },
    {
      "id": 17,
      "reference": "시편 103:2-4",
      "text": "내 영혼아 여호와를 송축하며 그의 모든 은택을 잊지 말지어다 그가 네 모든 죄악을 사하시며 네 모든 병을 고치시며 네 생명을 파멸에서 속량하시고 인자와 긍휼로 관을 씌우시며",
      "tags": ["gratitude", "healing", "forgiveness"]
    },
    {
      "id": 18,
      "reference": "골로새서 3:13",
      "text": "누가 누구에게 불만이 있거든 서로 용납하여 피차 용서하되 주께서 너희를 용서하신 것 같이 너희도 그리하고",
      "tags": ["forgiveness", "love", "patience"]
    },
    {
      "id": 19,
      "reference": "야고보서 1:5",
      "text": "너희 중에 누구든지 지혜가 부족하거든 모든 사람에게 후히 주시고 꾸짖지 아니하시는 하나님께 구하라 그리하면 주시리라",
      "tags": ["wisdom", "guidance"]
    },
    {
      "id": 20,
      "reference": "시편 147:3",
      "text": "그가 마음이 상한 자들을 고치시며 그들의 상처를 싸매시는도다",
      "tags": ["healing", "comfort", "love"]
    },
    {
      "id": 21,
      "reference": "데살로니가전서 5:16-18",
      "text": "항상 기뻐하라 쉬지 말고 기도하라 범사에 감사하라 이것이 그리스도 예수 안에서 너희를 향하신 하나님의 뜻이니라",
      "tags": ["joy", "gratitude", "peace"]
    },
    {
      "id": 22,
      "reference": "시편 119:105",
      "text": "주의 말씀은 내 발에 등이요 내 길에 빛이니이다",
      "tags": ["guidance", "wisdom"]
    },
    {
      "id": 23,
      "reference": "로마서 15:13",
      "text": "소망의 하나님이 모든 기쁨과 평강을 믿음 안에서 너희에게 충만하게 하사 성령의 능력으로 소망이 넘치게 하시기를 원하노라",
      "tags": ["hope", "joy", "peace", "faith"]
    },
    {
      "id": 24,
      "reference": "베드로전서 5:7",
      "text": "너희 염려를 다 주께 맡기라 이는 그가 너희를 돌보심이라",
      "tags": ["trust", "comfort", "peace"]
    },
    {
      "id": 25,
      "reference": "시편 42:11",
      "text": "내 영혼아 네가 어찌하여 낙심하며 어찌하여 내 속에서 불안해 하는가 너는 하나님께 소망을 두라 나는 그가 나타나 도우심으로 말미암아 내 하나님을 여전히 찬송하리로다",
      "tags": ["hope", "comfort", "trust"]
    },
    {
      "id": 26,
      "reference": "빌립보서 4:13",
      "text": "내게 능력 주시는 자 안에서 내가 모든 것을 할 수 있느니라",
      "tags": ["strength", "courage", "faith"]
    },
    {
      "id": 27,
      "reference": "시편 121:1-2",
      "text": "내가 산을 향하여 눈을 들리라 나의 도움이 어디서 올까 나의 도움은 천지를 지으신 여호와에게서로다",
      "tags": ["hope", "trust", "presence"]
    },
    {
      "id": 28,
      "reference": "에베소서 3:20",
      "text": "우리 가운데서 역사하시는 능력대로 우리가 구하거나 생각하는 모든 것에 더 넘치도록 능히 하실 이에게",
      "tags": ["faith", "hope", "strength"]
    },
    {
      "id": 29,
      "reference": "시편 139:14",
      "text": "내가 주께 감사하옴은 나를 지으심이 심히 기묘하심이라 주께서 하시는 일이 기이함을 내 영혼이 잘 아나이다",
      "tags": ["gratitude", "love", "joy"]
    },
    {
      "id": 30,
      "reference": "요한복음 16:33",
      "text": "이것을 너희에게 이르는 것은 너희로 내 안에서 평안을 누리게 하려 함이라 세상에서는 너희가 환난을 당하나 담대하라 내가 세상을 이기었노라",
      "tags": ["courage", "peace", "strength", "hope"]
    },
    {
      "id": 31,
      "reference": "시편 118:24",
      "text": "이 날은 여호와께서 정하신 것이라 이 날에 우리가 즐거워하고 기뻐하리로다",
      "tags": ["joy", "gratitude"]
    },
    {
      "id": 32,
      "reference": "시편 100:4-5",
      "text": "감사함으로 그의 문에 들어가며 찬송함으로 그의 궁정에 들어가서 그에게 감사하며 그의 이름을 송축할지어다 여호와는 선하시니 그의 인자하심이 영원하고 그의 성실하심이 대대에 이르리로다",
      "tags": ["gratitude", "joy", "faith"]
    },
    {
      "id": 33,
      "reference": "잠언 15:1",
      "text": "유순한 대답은 분노를 쉬게 하여도 과격한 말은 노를 격동하느니라",
      "tags": ["patience", "peace", "wisdom"]
    },
    {
      "id": 34,
      "reference": "에베소서 4:26-27",
      "text": "분을 내어도 죄를 짓지 말며 해가 지도록 분을 품지 말고 마귀에게 틈을 주지 말라",
      "tags": ["patience", "peace", "forgiveness"]
    },
    {
      "id": 35,
      "reference": "마태복음 6:14-15",
      "text": "너희가 사람의 잘못을 용서하면 너희 하늘 아버지께서도 너희 잘못을 용서하시려니와 너희가 사람의 잘못을 용서하지 아니하면 너희 아버지께서도 너희 잘못을 용서하지 아니하시리라",
      "tags": ["forgiveness", "love", "peace"]
    },
    {
      "id": 36,
      "reference": "고린도전서 13:4-7",
      "text": "사랑은 오래 참고 사랑은 온유하며 시기하지 아니하며 사랑은 자랑하지 아니하며 교만하지 아니하며 무례히 행하지 아니하며 자기의 유익을 구하지 아니하며 성내지 아니하며 악한 것을 생각하지 아니하며",
      "tags": ["love", "patience", "peace"]
    },
    {
      "id": 37,
      "reference": "빌립보서 4:11-12",
      "text": "내가 궁핍하므로 말하는 것이 아니니라 어떠한 형편에든지 나는 자족하기를 배웠노니 나는 비천에 처할 줄도 알고 풍부에 처할 줄도 알아 모든 일 곧 배부름과 배고픔과 풍부와 궁핍에도 처할 줄 아는 일체의 비결을 배웠노라",
      "tags": ["peace", "gratitude", "trust"]
    },
    {
      "id": 38,
      "reference": "히브리서 13:5",
      "text": "돈을 사랑하지 말고 있는 바를 족한 줄로 알라 그가 친히 말씀하시기를 내가 결코 너희를 버리지 아니하고 너희를 떠나지 아니하리라 하셨느니라",
      "tags": ["trust", "peace", "presence"]
    },
    {
      "id": 39,
      "reference": "요한일서 4:19",
      "text": "우리가 사랑함은 그가 먼저 우리를 사랑하셨음이라",
      "tags": ["love", "gratitude", "faith"]
    },
    {
      "id": 40,
      "reference": "시편 37:4",
      "text": "또 여호와를 기뻐하라 그가 네 마음의 소원을 네게 이루어 주시리로다",
      "tags": ["joy", "hope", "trust"]
    }
  ],
  "tagDescriptions": {
    "comfort": "위로",
    "hope": "희망",
    "peace": "평안",
    "strength": "힘",
    "courage": "용기",
    "rest": "쉼",
    "trust": "신뢰",
    "love": "사랑",
    "presence": "함께하심",
    "guidance": "인도",
    "wisdom": "지혜",
    "healing": "치유",
    "forgiveness": "용서",
    "patience": "인내",
    "gratitude": "감사",
    "joy": "기쁨",
    "faith": "믿음"
  },
  "encouragementMessages": {
    "_design": "4단계 구조: ①감정 검증(Validation) → ②심리 재구성(Reframe, 이론 근거) → ③구체적 성경 구절 연결 → ④행동 지향 클로징. 태그별 심리 패턴에 맞춘 개인화된 메시지.",
    "comfort": {
      "_theory": "Rogers 무조건적 공감 수용 + CBT 검증 우선 원칙: 위로가 필요하다는 것을 인정하는 것 자체가 용기임을 강조",
      "message": "오늘 마음이 많이 무거웠겠군요. 위로가 필요할 때 그것을 인정하는 것 자체가 용기예요. 하나님은 당신의 아픔을 외면하지 않으십니다 — '마음이 상한 자에게 가까이 하시는'(시편 34:18) 그분이 지금 이 순간도 당신 곁에 계세요.",
      "closing": "당신의 아픔을 그분께 내려놓아도 괜찮아요"
    },
    "hope": {
      "_theory": "Snyder(1994) 희망이론: 희망 = 목표 + 경로 사고(Pathways) + 동기(Agency). 막연한 낙관이 아닌 '다음 한 걸음'을 찾는 능동적 과정임을 강조",
      "message": "앞이 보이지 않는 막막함, 그 감정이 충분히 자연스러워요. 희망은 막연한 낙관이 아니라 — 지금 당장은 다 보이지 않아도 다음 한 걸음을 찾는 힘이에요. 하나님은 당신의 미래에 '평안이요 재앙이 아닌' 계획을 품고 계세요(예레미야 29:11). 작은 한 걸음부터 시작해도 돼요.",
      "closing": "작은 한 걸음이 새로운 길을 만들어가요"
    },
    "peace": {
      "_theory": "정서조절(Gross 2015) 인지 재평가 + 마음챙김(Kabat-Zinn): 평안은 불안의 부재가 아니라 그 안에서도 흔들리지 않는 중심임을 강조",
      "message": "마음이 분주하고 복잡한 것, 그대로 인정해도 괜찮아요. 평안은 모든 걱정이 사라진 상태가 아니라 — 그 안에서도 흔들리지 않는 중심이에요. 하나님의 평강은 '모든 지각에 뛰어나'(빌립보서 4:7) 우리 마음을 지켜주세요. 지금 숨을 고르고, 그분 앞에 내려놓아 보세요.",
      "closing": "내면의 고요함은 조건 없이 지금 여기서 시작돼요"
    },
    "strength": {
      "_theory": "Seligman PERMA 회복탄력성 + 학습된 무력감(Helplessness) 대응: 한계를 인정하는 것이 포기가 아닌 진정한 강함의 시작임을 강조",
      "message": "힘이 빠지고 지쳐있을 때, 그것은 나약함이 아니라 자신의 한계를 솔직하게 인정하는 용기예요. 하나님은 지친 자에게 새 힘을 주시는 분이에요(이사야 40:31). 지금 당신의 한계를 인정하고 그분께 기대는 것 자체가 진정한 강함이에요.",
      "closing": "여기까지 버텨온 것만으로도 당신은 이미 강한 사람이에요"
    },
    "courage": {
      "_theory": "Bandura(1977) 자기효능감 + ACT 가치 기반 행동: 용기는 두려움의 부재가 아니라 두려워도 가치에 따라 행동하는 것임을 강조",
      "message": "두려움은 사라져야 할 적이 아니에요 — 중요한 것 앞에 서 있다는 신호예요. 용기는 두려움이 없는 것이 아니라, 두려워도 한 걸음 내딛는 것이에요. '두려워하지 말라 내가 너와 함께 함이라'(이사야 41:10) — 완벽하지 않아도, 그분이 함께하세요.",
      "closing": "두려워도 괜찮아요 — 함께하시는 분이 있으니까요"
    },
    "rest": {
      "_theory": "정서조절 회복(Recovery) + 신체화 인식: 쉼은 게으름이 아니라 지속 가능성을 위한 필수 회복임을 강조",
      "message": "멈추는 것이 게으름이 아니에요 — 지속하기 위한 필수적인 회복이에요. 몸과 마음의 피로는 중요한 신호예요. '수고하고 무거운 짐 진 자들아 내게로 오라 내가 너희를 쉬게 하리라'(마태복음 11:28) — 그분 앞에서 그냥 쉬어도 괜찮아요.",
      "closing": "쉬는 것도 하나님께서 원하시는 것이에요"
    },
    "trust": {
      "_theory": "CBT 불확실성 내성(Intolerance of Uncertainty) + 인지 재평가: 불확실함이 버려짐을 의미하지 않으며, 통제 불가 상황에서 신뢰를 선택하는 것임을 강조",
      "message": "통제할 수 없는 것들이 많아 불안한 마음, 충분히 이해해요. 불확실함이 당신이 버려진 것을 의미하지 않아요. '너는 마음을 다하여 여호와를 신뢰하고 네 명철을 의지하지 말라'(잠언 3:5) — 알 수 없는 미래를 함께 걷는 분이 계세요.",
      "closing": "모르는 것이 있어도 괜찮아요 — 그분이 아시니까요"
    },
    "love": {
      "_theory": "Neff(2011) 자기연민 + 애착이론(Bowlby): 사랑은 취약함을 포함하며, 하나님의 선행적 사랑이 우리 사랑의 원천임을 강조",
      "message": "사랑한다는 것은 아름다운 만큼 취약해지는 것이기도 해요. 상처받을 수 있는데도 사랑하기로 선택하는 것은 하나님을 닮은 용기예요. '우리가 사랑함은 그가 먼저 우리를 사랑하셨음이라'(요한일서 4:19) — 당신의 사랑은 그분께 받은 것을 흘려보내는 것이에요.",
      "closing": "사랑하는 마음, 그것이 이미 하나님의 형상이에요"
    },
    "presence": {
      "_theory": "애착이론(Bowlby) 안전기지(Secure Base) + 사회적 고립 연구: 외로움 감정을 검증하면서도 더 깊은 연결의 실재를 안내",
      "message": "혼자라는 느낌은 매우 실제적이고 아픈 감정이에요 — 그 감정을 인정해도 괜찮아요. 동시에, 하나님은 '결코 떠나지 않겠다'(히브리서 13:5) 약속하신 분이에요. 당신이 느끼지 못하는 순간에도, 그분은 당신 곁에 계세요.",
      "closing": "혼자가 아님을 조금씩 알아가는 것, 그것도 용기예요"
    },
    "guidance": {
      "_theory": "CBT 행동 활성화(Behavioral Activation) + Snyder 경로 사고(Pathways Thinking): 하나님의 인도는 전체 지도가 아닌 한 걸음 앞의 등불임을 강조",
      "message": "어디로 가야 할지 모를 때, 그 막막함을 안고 기도하는 것이 이미 방향을 찾는 첫 걸음이에요. 하나님의 인도는 종종 한꺼번에 오지 않고, '발의 등'처럼 한 걸음 앞만 밝혀주실 때도 있어요(시편 119:105). 지금 보이는 작은 것부터 따라가 보세요.",
      "closing": "한 걸음 내딛으면 다음 길이 보여요"
    },
    "wisdom": {
      "_theory": "ACT 가치 명료화(Values Clarification) + Frankl 의미치료: 혼란이 깊은 지혜를 찾는 신호이며, 고요함 속에서 분별이 온다는 것을 강조",
      "message": "무엇이 진짜 중요한지 모르겠을 때, 그 혼란 자체가 더 깊은 지혜를 찾고 있다는 신호예요. 하나님께 지혜를 구하면 '꾸짖지 않고 후히 주신다'(야고보서 1:5)고 약속하셨어요. 선택 앞에서 잠시 멈추고, 그분께 묻는 것이 이미 지혜의 시작이에요.",
      "closing": "옳은 길은 고요함 속에서 더 잘 들려요"
    },
    "healing": {
      "_theory": "ACT 수용(Acceptance) + 정서조절 치유 과정: 치유는 선형이 아닌 순환적 과정이며, 회복 속도를 강요하지 않는 자기연민 강조",
      "message": "상처는 빨리 사라져야 한다는 압박을 내려놓아도 돼요. 치유는 직선이 아닌 — 아팠다 나아지기를 반복하는 과정이에요. 하나님은 '상한 자들을 고치시며 그 상처를 싸매시는'(시편 147:3) 분이에요. 오늘의 아픔도 그분 손 안에 있어요.",
      "closing": "당신의 회복 속도가 곧 당신의 속도예요"
    },
    "forgiveness": {
      "_theory": "Neff(2011) 자기연민 + CBT 자기비판 완화: 용서는 타인을 위한 것이 아닌 자신의 자유이며, 자기 용서도 포함함을 강조",
      "message": "용서는 상대를 위한 것이 아니에요 — 당신 자신이 짐에서 자유로워지는 것이에요. 나 자신을 향한 용서든, 다른 사람을 향한 용서든, 그 짐을 내려놓는 것은 하나님의 은혜를 받아들이는 것과 같아요. '주께서 너희를 용서하신 것 같이'(골로새서 3:13) — 그 은혜가 당신에게도 있어요.",
      "closing": "용서는 힘으로가 아니라 은혜로 오는 거예요"
    },
    "patience": {
      "_theory": "Ellis REBT 좌절 내성(LFT) 강화 + 의미치료(Frankl): 인내는 수동적 기다림이 아닌 현재를 의미 있게 살아가는 것임을 강조",
      "message": "기다림이 답답하게 느껴지는 것, 당연해요 — 그 감정을 억누를 필요가 없어요. 인내는 수동적 기다림이 아니라, 지금 이 순간도 의미 있게 살아가는 것이에요. '여호와를 앙망하는 자는 새 힘을 얻으리니'(이사야 40:31) — 기다리는 동안에도 하나님은 일하고 계세요.",
      "closing": "기다리는 동안에도 당신은 성장하고 있어요"
    },
    "gratitude": {
      "_theory": "Emmons&McCullough(2003) 감사 연구 + Fredrickson(2001) Broaden-and-Build: 감사는 현실 외면이 아닌 능동적 선택이며 뇌와 정서 상태를 실제로 변화시킴",
      "message": "감사는 현실을 외면하는 게 아니에요 — 어려움 속에서도 선함을 발견하는 능동적인 선택이에요. 감사하는 마음이 우리 뇌와 마음의 상태를 실제로 변화시킨다는 것이 연구로 밝혀졌어요. '범사에 감사하라'(데살로니가전서 5:18) — 이 말씀이 당신을 위한 처방이에요.",
      "closing": "감사하는 눈이 더 많은 은혜를 보게 해줘요"
    },
    "joy": {
      "_theory": "Bryant&Veroff(2007) Savoring + Fredrickson Broaden-and-Build: 기쁨을 서둘러 지나치지 않고 의식적으로 음미하는 것이 행복의 지속성을 높임",
      "message": "오늘의 기쁨, 충분히 누려도 좋아요 — 이 순간을 음미하는 것이 더 큰 행복의 토양이 돼요. 기쁨을 서둘러 지나치지 말고, 잠시 이 감사함 안에 머물러 보세요. '여호와를 기뻐하라 그가 네 마음의 소원을 이루어 주시리로다'(시편 37:4) — 하나님 안에서의 기쁨은 자라나요.",
      "closing": "오늘의 기쁨이 내일의 씨앗이 돼요"
    },
    "faith": {
      "_theory": "ACT 가치 기반 행동 + 의심과 공존하는 믿음: 믿음은 확신의 충만함이 아니라 불확실함 속에서도 한 걸음 걷는 것임을 강조",
      "message": "믿음은 확신이 충만할 때만 있는 것이 아니에요 — 의심과 함께 걸어가는 것도 믿음이에요. 하나님은 당신의 의심도 두려워하지 않으세요. '믿음은 바라는 것들의 실상이요 보이지 않는 것들의 증거'(히브리서 11:1) — 보이지 않아도 한 걸음씩 걷는 것, 그게 진짜 믿음이에요.",
      "closing": "완전하지 않은 믿음도 하나님은 받으세요"
    },
    "default": {
      "_theory": "자기돌봄(Self-care) + 시편 139 전지하심: 감정을 살피는 행위 자체를 가치 있게 인정",
      "message": "오늘 자신의 마음을 들여다보는 시간을 가지셨군요. 감정을 살피고 돌보는 것 자체가 값진 일이에요. 하나님은 당신의 생각과 마음을 속속들이 아시고(시편 139:1-4), 그 모든 것 안에서도 당신을 사랑하세요. 오늘도 수고하셨어요.",
      "closing": "자신을 돌보는 일, 계속 이어가세요"
    }
  }
}
